polygon_session/__init__.py
polygon_session-0.0.1.dist-info/METADATA
polygon_session-0.0.1.dist-info/WHEEL
polygon_session-0.0.1.dist-info/RECORD
